hasspad/__init__.py
hasspad/config.py
hasspad/handlers/__init__.py
hasspad/handlers/base.py
hasspad/handlers/light.py
hasspad/hasspad.py
hasspad/main.py
hasspad-0.1.3.dist-info/entry_points.txt
hasspad-0.1.3.dist-info/LICENSE
hasspad-0.1.3.dist-info/WHEEL
hasspad-0.1.3.dist-info/METADATA
hasspad-0.1.3.dist-info/RECORD
