Metadata-Version: 2.1
Name: hasspad
Version: 0.1.3
Summary: 
Home-page: https://github.com/kvchen/hasspad/
License: MIT
Keywords: Home Assistant,keybow
Author: Kevin Chen
Author-email: keffcat@gmail.com
Requires-Python: >=3.8,<4.0
Classifier: License :: OSI Approved :: MIT License
Classifier: Programming Language :: Python :: 3
Classifier: Programming Language :: Python :: 3.8
Classifier: Programming Language :: Python :: 3.9
Requires-Dist: PyYAML (>=5.4.1,<6.0.0)
Requires-Dist: RPi.GPIO (>=0.7.0,<0.8.0)
Requires-Dist: click (>=7.1.2,<8.0.0)
Requires-Dist: keybow (>=0.0.3,<0.0.4)
Requires-Dist: pydantic (>=1.7.3,<2.0.0)
Requires-Dist: rich (>=9.8.2,<10.0.0)
Requires-Dist: spidev (>=3.5,<4.0)
Requires-Dist: websockets (>=8.1,<9.0)
Project-URL: Repository, https://github.com/kvchen/hasspad/
